moveable_morphable_components/__init__.py
moveable_morphable_components/components.py
moveable_morphable_components/domain.py
moveable_morphable_components/finite_element.py
moveable_morphable_components/layout.py
moveable_morphable_components/main.py
moveable_morphable_components/method_moving_asymptotes.py
moveable_morphable_components/plot.py
moveable_morphable_components-0.6.0.dist-info/METADATA
moveable_morphable_components-0.6.0.dist-info/WHEEL
moveable_morphable_components-0.6.0.dist-info/licenses/LICENSE
moveable_morphable_components-0.6.0.dist-info/RECORD
