Metadata-Version: 2.3
Name: moveable-morphable-components
Version: 0.6.0
Summary: An implementation of the Moveable Morphable Components algorithm
Project-URL: Documentation, https://jonathanraines.github.io/moveable-morphable-components/
Project-URL: Repository, https://github.com/JonathanRaines/moveable-morphable-components
Project-URL: Issues, https://github.com/JonathanRaines/moveable-morphable-components/issues
Author-email: Jonathan Raines <jonathan.raines@bristol.ac.uk>
License:                     GNU GENERAL PUBLIC LICENSE
License-File: LICENSE
Requires-Python: >=3.10.12
Requires-Dist: jax[cuda12]==0.4.33
Requires-Dist: kaleido==0.2.1
Requires-Dist: networkx>=3.4.1
Requires-Dist: numpy>=2.1.2
Requires-Dist: pandas==2.2.2
Requires-Dist: pillow==10.4.0
Requires-Dist: plotly>=5.24.1
Requires-Dist: scipy==1.14.0
Requires-Dist: sympy==1.13.1
Requires-Dist: torch>=2.0.1
Requires-Dist: tqdm>=4.66.5
